datateam_moss/__init__.py
datateam_moss/bronanalyse.py
datateam_moss/cleaning.py
datateam_moss/controles.py
datateam_moss/datamodelleren.py
datateam_moss/deltatabel_aanpassingen.py
datateam_moss/initialization.py
datateam_moss/logger.py
datateam_moss/privacy.py
datateam_moss/reversed_modeling.py
datateam_moss/scd_historiseren.py
datateam_moss/spark_io_utils.py
datateam_moss-0.2.5.dist-info/licenses/LICENSE
datateam_moss-0.2.5.dist-info/METADATA
datateam_moss-0.2.5.dist-info/WHEEL
datateam_moss-0.2.5.dist-info/top_level.txt
datateam_moss-0.2.5.dist-info/RECORD
