Metadata-Version: 2.4
Name: datateam_moss
Version: 0.2.5
Summary: Functions needed for datateam MOSS (municipality of Amsterdam)
Author-email: XX <x@x.nl>
Requires-Python: >=3.10
License-File: LICENSE
Requires-Dist: tabulate==0.9.0
Requires-Dist: xxhash==3.4.1
Requires-Dist: opentelemetry-sdk==1.39.0
Requires-Dist: azure-monitor-opentelemetry-exporter==1.0.0b46
Requires-Dist: azure-mgmt-monitor==7.0.0
Requires-Dist: pandas==1.4.4
Dynamic: license-file
